models/__init__.py
models/enums.py
models/reminder.py
services/__init__.py
services/antenatal_scheduler.py
services/location_service.py
services/notification_manager.py
services/reminder_manager.py
services/types.py
services/voice_service.py
services/weather_service.py
storage/__init__.py
storage/json_storage.py
tests/__init__.py
tests/test_system_integration.py
reminder_manager-0.0.1.dist-info/METADATA
reminder_manager-0.0.1.dist-info/WHEEL
reminder_manager-0.0.1.dist-info/top_level.txt
reminder_manager-0.0.1.dist-info/RECORD
