Metadata-Version: 2.1
Name: reminder_manager
Version: 0.0.1
Summary: A reminder management system
Home-page: https://github.com/yourusername/reminder_manager
Author: Iga Martin
Author-email: <your-actual-email@example.com>
License: MIT
Keywords: python,reminder,pregnancy,healthcare,hospital
Classifier: License :: OSI Approved :: MIT License
Classifier: Development Status :: 4 - Beta
Classifier: Intended Audience :: Developers
Classifier: Programming Language :: Python :: 3
Classifier: Operating System :: Unix
Classifier: Operating System :: MacOS :: MacOS X
Classifier: Operating System :: Microsoft :: Windows
Requires-Python: >=3.6.0
Requires-Dist: portalocker
Requires-Dist: pytest
Requires-Dist: googlemaps
Requires-Dist: requests
Requires-Dist: pyttsx3
Requires-Dist: playsound
Requires-Dist: schedule
Requires-Dist: scipy
Requires-Dist: pydub
Requires-Dist: numpy
